MANIFEST.in
README.md
requirements.txt
setup.cfg
setup.py
fex/__init__.py
fex/collection.py
fex/feature_extractor.py
fex/runner.py
fex.egg-info/PKG-INFO
fex.egg-info/SOURCES.txt
fex.egg-info/dependency_links.txt
fex.egg-info/requires.txt
fex.egg-info/top_level.txt