Metadata-Version: 1.0
Name: fex
Version: 0.2.1
Summary: Bayes Impact feature extraction framework.
